typeshed_stats/__init__.py
typeshed_stats/__main__.py
typeshed_stats/_cli.py
typeshed_stats/_markdown_template.md.jinja
typeshed_stats/_version.py
typeshed_stats/gather.py
typeshed_stats/py.typed
typeshed_stats/serialize.py
typeshed_stats-26.2.1.dist-info/METADATA
typeshed_stats-26.2.1.dist-info/WHEEL
typeshed_stats-26.2.1.dist-info/entry_points.txt
typeshed_stats-26.2.1.dist-info/licenses/LICENSE
typeshed_stats-26.2.1.dist-info/RECORD
