Metadata-Version: 2.4
Name: typeshed_stats
Version: 26.2.1
Summary: Library and command-line tool to gather stats on typeshed packages
Project-URL: Homepage, https://github.com/AlexWaygood/typeshed-stats
Project-URL: Bug Tracker, https://github.com/AlexWaygood/typeshed-stats/issues
Author-email: Alex Waygood <alex.waygood@gmail.com>
License: MIT
License-File: LICENSE
Keywords: stubs,typeshed,typing
Classifier: Development Status :: 3 - Alpha
Classifier: Intended Audience :: Developers
Classifier: License :: OSI Approved :: MIT License
Classifier: Operating System :: OS Independent
Classifier: Programming Language :: Python
Classifier: Programming Language :: Python :: 3 :: Only
Classifier: Programming Language :: Python :: 3.11
Classifier: Programming Language :: Python :: 3.12
Classifier: Programming Language :: Python :: 3.13
Classifier: Programming Language :: Python :: 3.14
Classifier: Topic :: Software Development
Classifier: Typing :: Typed
Requires-Python: >=3.11
Requires-Dist: aiohttp[speedups]>=3.9.0
Requires-Dist: attrs>=22.2.0
Requires-Dist: cattrs
Requires-Dist: jinja2>=3
Requires-Dist: packaging
Requires-Dist: pathspec>=1
Provides-Extra: rich
Requires-Dist: rich; extra == 'rich'
Requires-Dist: rich-argparse>=1; extra == 'rich'
